MANIFEST.in
README.md
setup.py
dash_file_dialog_components/DashFileDialogComponents.py
dash_file_dialog_components/__init__.py
dash_file_dialog_components/_imports_.py
dash_file_dialog_components/dash_file_dialog_components.dev.js
dash_file_dialog_components/dash_file_dialog_components.min.js
dash_file_dialog_components/metadata.json
dash_file_dialog_components/package.json
dash_file_dialog_components.egg-info/PKG-INFO
dash_file_dialog_components.egg-info/SOURCES.txt
dash_file_dialog_components.egg-info/dependency_links.txt
dash_file_dialog_components.egg-info/top_level.txt