Metadata-Version: 1.0
Name: dash-file-dialog-components
Version: 0.0.1
Summary: File Dialog Component for Dash
Home-page: UNKNOWN
Author: Lukasz Tracewski lukasz.tracewski@outlook.com
Author-email: UNKNOWN
License: MIT
Platform: UNKNOWN
